LICENSE.txt
MANIFEST.in
README.rst
setup.py
pymamba/__init__.py
pymamba/models.py
pymamba/types.py
pymamba.egg-info/PKG-INFO
pymamba.egg-info/SOURCES.txt
pymamba.egg-info/dependency_links.txt
pymamba.egg-info/requires.txt
pymamba.egg-info/top_level.txt