Metadata-Version: 1.1
Name: pymamba
Version: 0.2.3
Summary: Database library for Python based on LMDB storage engine
Home-page: https://github.com/oddjobz/pymamba
Author: Gareth Bult
Author-email: oddjobz@linux.co.uk
License: MIT
Keywords: pymamba,database,LMDB,python,ORM
Platform: UNKNOWN
Classifier: Development Status :: 3 - Alpha
Classifier: Intended Audience :: Developers
Classifier: Topic :: Database :: Database Engines/Servers
Classifier: License :: OSI Approved :: MIT License
Classifier: Programming Language :: Python :: 3.5
